varphi_types/__init__.py
varphi_types/varphi_types.py
varphi_types-0.0.4.dist-info/LICENSE
varphi_types-0.0.4.dist-info/METADATA
varphi_types-0.0.4.dist-info/WHEEL
varphi_types-0.0.4.dist-info/top_level.txt
varphi_types-0.0.4.dist-info/RECORD
