Metadata-Version: 2.1
Name: varphi_types
Version: 0.0.4
Summary: Common types for Varphi tools.
Home-page: https://github.com/hassanelsheikha/varphi_types
Author: Hassan El-Sheikha
Author-email: hassan.elsheikha@utoronto.ca
Classifier: Programming Language :: Python :: 3
Classifier: License :: OSI Approved :: BSD License
Classifier: Operating System :: OS Independent
License-File: LICENSE
